Workbook

Sheet Executive Summary
A1: TOP PERFORMER — EXECUTIVE COST SUMMARY
A3: KEY METRICS | B3: Amount | C3: Source
A4: Elite Subscription Price | B4: ='Unit Economics'!B5 -> 19.99 | C4: Monthly price
A5: Your Revenue After Apple (Year 1) | B5: ='Unit Economics'!B8 -> 13.993 | C5: After 30% commission
A6: Claude API Cost Per User Per Month | B6: ='Unit Economics'!B33 -> 15.7005 | C6: Based on avg usage
A7: Gross Profit Per User Per Month | B7: ='Unit Economics'!B37 -> -1.7075 | C7: Revenue minus API
A9: MONTHLY INFRASTRUCTURE
A10: Total Fixed Costs (starter tier) | B10: ='Break-Even Analysis'!B17 -> 93.25 | C10: Render + services
A12: ★ BREAK-EVEN
A13: Paying subscribers needed to break even | B13: ='Break-Even Analysis'!B38 -> -55 | C13: At current fixed costs and per-user margins
A15: MONTHLY P&L AT KEY MILESTONES
A16: Net Profit at 100 subscribers | B16: ='Break-Even Analysis'!C32 -> -264
A17: Net Profit at 500 subscribers | B17: ='Break-Even Analysis'!E32 -> -1007
A18: Net Profit at 1,000 subscribers | B18: ='Break-Even Analysis'!F32 -> -1916.75
A20: BUSINESS ENTITY RECOMMENDATION
A21: Start as Single-Member LLC (~$100-300 to form). Elect S-Corp when net profit exceeds $50K/yr to save $2K-10K/yr in self-employment taxes.
A23: IP PROTECTION — IMMEDIATE ACTIONS
A24: 1. File LLC in your state ($50-300)
A25: 2. File 'Top Performer' trademark via USPTO TEAS Plus ($250-350)
A26: 3. Register topperformer.app domain ($12-15)
A27: 4. Secure @topperformer on all social platforms ($0)
A28: 5. Register Content Bible copyright with US Copyright Office ($65)
A29: 6. Add © 2026 Top Performer LLC to app footer ($0)
A30: 7. Mark Content Bible + system prompt as CONFIDENTIAL trade secrets ($0)
A31: 8. Apply for Apple Small Business Program to reduce commission to 15%

Sheet Unit Economics
A1: TOP PERFORMER — UNIT ECONOMICS & COST ANALYSIS
A2: All blue values are editable assumptions. Black values are calculated.
A4: REVENUE PER SUBSCRIBER | B4: Value | C4: Notes
A5: Elite Monthly Price | B5: 19.99 | C5: User-facing price
A6: Apple Commission Rate (Year 1) | B6: 0.3 | C6: Standard 30% cut
A7: Apple Commission Rate (Year 2+) | B7: 0.15 | C7: Small Business Program (<$1M rev)
A8: Net Revenue Per Sub (Year 1) | B8: =B5*(1-B6) -> 13.993 | C8: After Apple's 30%
A9: Net Revenue Per Sub (Year 2+) | B9: =B5*(1-B7) -> 16.9915 | C9: After Apple's 15%
A10: First Month Free Cost (forgone rev) | B10: =B8 -> 13.993 | C10: Revenue you don't collect month 1
A11: Effective Monthly Rev (if retained 12mo) | B11: =B8*11/12 -> 12.826917 | C11: Net rev × 11/12 (free month spread)
A13: CLAUDE API COSTS | B13: Value | C13: Notes
A14: Model | B14: claude-sonnet-4 | C14: From claude.js config
A15: Input Price (per 1M tokens) | B15: 3 | C15: Sonnet 4 pricing
A16: Output Price (per 1M tokens) | B16: 15 | C16: Sonnet 4 pricing
A17: System Prompt Size (tokens) | B17: 16000 | C17: ~64,658 chars from buildSystemPrompt()
A18: Avg User Message (tokens) | B18: 150 | C18: Typical user coaching question
A19: Avg History Context (tokens) | B19: 4000 | C19: ~20 msgs × 200 tokens avg
A20: Max Output Tokens | B20: 1024 | C20: From claude.js MAX_TOKENS
A21: Avg Actual Output (tokens) | B21: 600 | C21: Typical coaching response
A22: Prompt Cache Hit Rate | B22: 0.8 | C22: System prompt cached across convos
A23: Prompt Cache Discount | B23: 0.9 | C23: Cached tokens cost 10% of normal
A24: --- PER CONVERSATION ---
A25: Total Input Tokens | B25: =B17+B19+B18 -> 20150 | C25: System + history + user msg
A26: Effective Input Cost / Conversation | B26: =((B17*B22*(1-B23)+B17*(1-B22)+B19+B18)/1000000)*B15 -> 0.02589 | C26: With prompt caching on system prompt
A27: Output Cost / Conversation | B27: =(B21/1000000)*B16 -> 0.009 | C27: Avg output tokens × output price
A28: Total API Cost / Conversation | B28: =B26+B27 -> 0.03489 | C28: Input + Output
A29: --- PER USER / MONTH ---
A30: Avg Conversations / User / Day | B30: 3 | C30: Active coaching user estimate
A31: Avg Messages / Conversation | B31: 5 | C31: Back-and-forth exchanges
A32: API Calls / User / Month | B32: =B30*B31*30 -> 450 | C32: Convos × messages × 30 days
A33: Claude API Cost / User / Month | B33: =B32*B28 -> 15.7005 | C33: API calls × cost per call
A34: --- GROSS MARGIN ---
A35: Net Revenue / User / Month (Yr1) | B35: =B8 -> 13.993
A36: API Cost / User / Month | B36: =B33 -> 15.7005
A37: Gross Profit / User / Month | B37: =B35-B33 -> -1.7075 | C37: Net rev minus API cost
A38: Gross Margin % | B38: =IF(B35=0,0,B37/B35) -> -0.1220253

Sheet Break-Even Analysis
A1: BREAK-EVEN ANALYSIS — MONTHLY P&L AT SCALE
B3: 50 Users | C3: 100 Users | D3: 250 Users | E3: 500 Users | F3: 1,000 Users | G3: 5,000 Users
A4: FIXED COSTS (MONTHLY)
A5: Render Web Service (Backend) | B5: 25 | C5: 25 | D5: 25 | E5: 25 | F5: 25 | G5: 25
A6: Render Static Site (Frontend) | B6: 0 | C6: 0 | D6: 0 | E6: 0 | F6: 0 | G6: 0
A7: Render PostgreSQL | B7: 19 | C7: 19 | D7: 19 | E7: 19 | F7: 19 | G7: 19
A8: Render Redis | B8: 10 | C8: 10 | D8: 10 | E8: 10 | F8: 10 | G8: 10
A9: Render Workspace (Professional) | B9: 19 | C9: 19 | D9: 19 | E9: 19 | F9: 19 | G9: 19
A10: Sentry Error Tracking | B10: 0 | C10: 0 | D10: 0 | E10: 0 | F10: 0 | G10: 0
A11: Mixpanel Analytics | B11: 0 | C11: 0 | D11: 0 | E11: 0 | F11: 0 | G11: 0
A12: Apple Developer Account | B12: 8.25 | C12: 8.25 | D12: 8.25 | E12: 8.25 | F12: 8.25 | G12: 8.25
A13: Domain + DNS | B13: 2 | C13: 2 | D13: 2 | E13: 2 | F13: 2 | G13: 2
A14: Misc (backups, monitoring) | B14: 10 | C14: 10 | D14: 10 | E14: 10 | F14: 10 | G14: 10
A15: Render Upgrade (Standard → Pro @ 500+) | B15: 0 | C15: 0 | D15: 0 | E15: 60 | F15: 60 | G15: 60
A16: DB Upgrade (1GB → 4GB @ 1000+) | B16: 0 | C16: 0 | D16: 0 | E16: 0 | F16: 56 | G16: 56
A17: TOTAL FIXED COSTS | B17: =SUM(B5:B16) -> 93.25 | C17: =SUM(C5:C16) -> 93.25 | D17: =SUM(D5:D16) -> 93.25 | E17: =SUM(E5:E16) -> 153.25 | F17: =SUM(F5:F16) -> 209.25 | G17: =SUM(G5:G16) -> 209.25
A19: VARIABLE COSTS (MONTHLY)
A20: Claude API Cost / User / Month | B20: ='Unit Economics'!B33 -> 15.7005 | C20: ='Unit Economics'!B33 -> 15.7005 | D20: ='Unit Economics'!B33 -> 15.7005 | E20: ='Unit Economics'!B33 -> 15.7005 | F20: ='Unit Economics'!B33 -> 15.7005 | G20: ='Unit Economics'!B33 -> 15.7005
A21: Paying Users (assume 100% of total) | B21: 50 | C21: 100 | D21: 250 | E21: 500 | F21: 1000 | G21: 5000
A22: TOTAL VARIABLE COSTS | B22: =B20*B21 -> 785.025 | C22: =C20*C21 -> 1570.05 | D22: =D20*D21 -> 3925.125 | E22: =E20*E21 -> 7850.25 | F22: =F20*F21 -> 15700.5 | G22: =G20*G21 -> 78502.5
A24: REVENUE (MONTHLY)
A25: Net Revenue / User / Month | B25: ='Unit Economics'!B35 -> 13.993 | C25: ='Unit Economics'!B35 -> 13.993 | D25: ='Unit Economics'!B35 -> 13.993 | E25: ='Unit Economics'!B35 -> 13.993 | F25: ='Unit Economics'!B35 -> 13.993 | G25: ='Unit Economics'!B35 -> 13.993
A26: TOTAL REVENUE | B26: =B25*B21 -> 699.65 | C26: =C25*C21 -> 1399.3 | D26: =D25*D21 -> 3498.25 | E26: =E25*E21 -> 6996.5 | F26: =F25*F21 -> 13993 | G26: =G25*G21 -> 69965
A28: NET PROFIT / LOSS (MONTHLY)
A29: Total Revenue | B29: =B26 -> 699.65 | C29: =C26 -> 1399.3 | D29: =D26 -> 3498.25 | E29: =E26 -> 6996.5 | F29: =F26 -> 13993 | G29: =G26 -> 69965
A30: Total Fixed Costs | B30: =B17 -> 93.25 | C30: =C17 -> 93.25 | D30: =D17 -> 93.25 | E30: =E17 -> 153.25 | F30: =F17 -> 209.25 | G30: =G17 -> 209.25
A31: Total Variable Costs | B31: =B22 -> 785.025 | C31: =C22 -> 1570.05 | D31: =D22 -> 3925.125 | E31: =E22 -> 7850.25 | F31: =F22 -> 15700.5 | G31: =G22 -> 78502.5
A32: MONTHLY NET PROFIT / (LOSS) | B32: =B26-B17-B22 -> -178.625 | C32: =C26-C17-C22 -> -264 | D32: =D26-D17-D22 -> -520.125 | E32: =E26-E17-E22 -> -1007 | F32: =F26-F17-F22 -> -1916.75 | G32: =G26-G17-G22 -> -8746.75
A33: Net Margin % | B33: =IF(B26=0,0,B32/B26) -> -0.25530622 | C33: =IF(C26=0,0,C32/C26) -> -0.18866576 | D33: =IF(D26=0,0,D32/D26) -> -0.14868148 | E33: =IF(E26=0,0,E32/E26) -> -0.14392911 | F33: =IF(F26=0,0,F32/F26) -> -0.1369792 | G33: =IF(G26=0,0,G32/G26) -> -0.12501608
A35: BREAK-EVEN POINT
A36: Fixed Costs (current tier) | B36: =B17 -> 93.25
A37: Contribution Margin / User | B37: ='Unit Economics'!B35-'Unit Economics'!B33 -> -1.7075 | C37: Net rev minus variable cost per user
A38: ★ BREAK-EVEN: PAYING SUBSCRIBERS NEEDED | B38: =ROUNDUP(B36/B37,0) -> -55

Sheet Cost Optimization
A1: COST OPTIMIZATION STRATEGIES
A3: API COST REDUCTION
A4: Switch to Claude 3.5 Haiku for simple queries | B4: 50-70% savings | C4: Route greetings, mood logs, simple Qs to Haiku ($1/$5 per MTok)
A5: Enable prompt caching | B5: Up to 90% on system prompt | C5: Cache the 16K-token system prompt; only pay 10% on cache hits
A6: Reduce system prompt size | B6: 20-40% savings | C6: Trim from 16K to 8-10K tokens; remove redundant instructions
A7: Shorten conversation history | B7: 15-25% savings | C7: Send last 10 messages instead of 20; summarize older context
A8: Lower max_tokens to 512 | B8: ~40% output savings | C8: Most coaching responses don't need 1024 tokens
A9: Implement response streaming | B9: Better UX, same cost | C9: Users see response faster; can abort early saving partial tokens
A10: Batch non-urgent requests | B10: 50% with Batch API | C10: Nightly insights, weekly summaries can use async Batch API
A12: INFRASTRUCTURE SAVINGS
A13: Use Render free tier initially | B13: $25-35/mo savings | C13: Start on free web service + free Redis until you hit limits
A14: Connection pooling for PostgreSQL | B14: Delay DB upgrade | C14: PgBouncer keeps you on smaller DB tier longer
A15: CDN for static assets | B15: Reduce bandwidth | C15: Cloudflare free tier for frontend; reduce Render egress
A17: REVENUE OPTIMIZATION
A18: Apple Small Business Program | B18: 15% vs 30% cut | C18: Apply immediately; cuts commission in half under $1M revenue
A19: Annual plan push (2 months free) | B19: Better retention, upfront cash | C19: $199.99/yr = $16.67 effective/mo; reduces churn
A20: Web-direct subscriptions (Stripe) | B20: Save 27% vs Apple | C20: Stripe takes ~3% vs Apple 30%; offer web signup option
A21: Referral program | B21: Lower CAC | C21: Existing users bring friends; no paid acquisition cost

Sheet Business Entity & IP
A1: BUSINESS ENTITY COMPARISON & IP PROTECTION STRATEGY
A3: LLC vs S-CORP COMPARISON | B3: Single-Member LLC | C3: Multi-Member LLC | D3: S-Corporation
A4: Formation Cost | B4: $50-500 (state filing) | C4: $50-500 + operating agreement | D4: $50-500 filing + S-Corp election
A5: Annual Maintenance | B5: $0-800 (state fees only) | C5: $0-800 (state fees only) | D5: $1,000-3,000 (payroll, tax prep)
A6: Liability Protection | B6: ✅ Full personal asset protection | C6: ✅ Full personal asset protection | D6: ✅ Full personal asset protection
A7: Taxation | B7: Pass-through (Schedule C) | C7: Pass-through (Form 1065) | D7: Pass-through (Form 1120-S)
A8: Self-Employment Tax | B8: Pay on ALL net income (15.3%) | C8: Pay on ALL net income (15.3%) | D8: Only on salary; distributions exempt
A9: SE Tax Savings @ $100K profit | B9: $0 saved | C9: $0 saved | D9: ~$5,000-10,000/yr saved
A10: SE Tax Savings @ $50K profit | B10: $0 saved | C10: $0 saved | D10: ~$2,000-4,000/yr saved
A11: Payroll Required? | B11: No | C11: No | D11: Yes — must pay yourself 'reasonable salary'
A12: Complexity | B12: ★☆☆ Very simple | C12: ★★☆ Moderate | D12: ★★★ Complex (payroll, minutes, etc.)
A13: Best For Revenue Under $50K/yr | B13: ✅ RECOMMENDED | C13: If partners needed | D13: Not worth the overhead
A14: Best For Revenue $50K-$150K/yr | B14: Good | C14: If partners needed | D14: ✅ RECOMMENDED — SE tax savings
... A17: App Store IP Ownership | B17: You own it personally | C17: LLC owns it | D17: S-Corp owns it
A19: ★ RECOMMENDATION: Start as Single-Member LLC now. Elect S-Corp status when net profit exceeds ~$50K/year.
A21: IP PROTECTION STRATEGY | B21: Priority | C21: Est. Cost | D21: Action Items
A22: TRADEMARKS
A23: File 'Top Performer' trademark (USPTO) | B23: 🔴 HIGH | C23: $250-350 | D23: File Intent-to-Use via TEAS Plus; Class 9 (software) + Class 42 (SaaS)
A24: File 'Bet On Yourself' trademark | B24: 🟡 MEDIUM | C24: $250-350 | D24: Secondary mark; file after primary if budget allows
A25: Register logo/icon mark | B25: 🟡 MEDIUM | C25: $250-350 | D25: File design mark separately for app icon
A27: COPYRIGHT
A28: Register Content Bible with US Copyright Office | B28: 🔴 HIGH | C28: $65 | D28: Protects your coaching methodology and content framework
A29: Register app source code | B29: 🟡 MEDIUM | C29: $65 | D29: Provides statutory damages option if code is stolen
A30: Copyright notice in app footer | B30: 🔴 HIGH | C30: $0 | D30: Add '© 2026 Top Performer LLC. All rights reserved.'
A32: TRADE SECRETS
A33: System prompt is a trade secret | B33: 🔴 HIGH | C33: $0 | D33: Already have confidentiality directive; never expose in client-side code
A34: Coaching methodology documentation | B34: 🔴 HIGH | C34: $0 | D34: Mark Content Bible as 'CONFIDENTIAL — TRADE SECRET'
A35: User engagement algorithms | B35: 🟡 MEDIUM | C35: $0 | D35: Document proprietary conversation mode logic
A37: APP STORE PROTECTIONS
A38: Secure all social handles (@topperformer) | B38: 🔴 HIGH | C38: $0 | D38: Instagram, TikTok, X, YouTube, Facebook, LinkedIn
A39: Register domain (topperformer.app) | B39: 🔴 HIGH | C39: $12-15/yr | D39: Primary domain + topperformerapp.com
A40: App Store brand protection | B40: 🟡 MEDIUM | C40: $0 | D40: Monitor for copycat apps; file takedowns via App Store
A42: CONTRACTS & AGREEMENTS
A43: Terms of Service | B43: 🔴 HIGH | C43: $0-500 | D43: Cover IP ownership, user-generated content rights, limitations
A44: Privacy Policy (already built) | B44: ✅ DONE | C44: $0 | D44: PrivacyPolicy.js already in app
A45: Contributor/contractor agreements | B45: 🟡 MEDIUM | C45: $0-200 | D45: If anyone helps build — ensure IP assignment clause
A46: NDA template | B46: 🟡 MEDIUM | C46: $0 | D46: For anyone who sees system prompt or proprietary methods
A48: ESTIMATED TOTAL IP PROTECTION BUDGET: ~$900-$1,600 (one-time) + ~$27/yr (domains, renewals)
